<?xml version="1.0" encoding="UTF-8"?><?xml-stylesheet type='text/xsl' href='_UpgradeReport_Files/UpgradeReport.xslt'?><UpgradeLog>
<Properties><Property Name="Solution" Value="nogg-gui">
</Property><Property Name="Solution File" Value="F:\Media\Games\World of Warcraft\Model Editing\Programs &amp; Tools\M2\3DSMtoM2\3dsToM2 GUI\nogg-gui.sln">
</Property><Property Name="User Options File" Value="F:\Media\Games\World of Warcraft\Model Editing\Programs &amp; Tools\M2\3DSMtoM2\3dsToM2 GUI\nogg-gui.suo">
</Property><Property Name="Date" Value="Monday, May 14, 2012">
</Property><Property Name="Time" Value="3:34 AM">
</Property></Properties><Event ErrorLevel="0" Project="" Source="nogg-gui.sln" Description="File successfully backed up as F:\Media\Games\World of Warcraft\Model Editing\Programs &amp; Tools\M2\3DSMtoM2\3dsToM2 GUI\Backup\nogg-gui.sln">
</Event><Event ErrorLevel="0" Project="" Source="nogg-gui.suo" Description="File successfully backed up as F:\Media\Games\World of Warcraft\Model Editing\Programs &amp; Tools\M2\3DSMtoM2\3dsToM2 GUI\Backup\nogg-gui.suo">
</Event><Event ErrorLevel="0" Project="" Source="nogg-gui.sln" Description="Solution converted successfully">
</Event><Event ErrorLevel="3" Project="" Source="nogg-gui.sln" Description="Converted">
</Event></UpgradeLog>